singlecell_cookbook/__init__.py
singlecell_cookbook/tools/__init__.py
singlecell_cookbook/tools/analysis/__init__.py
singlecell_cookbook/tools/analysis/_go_enrichment.py
singlecell_cookbook/tools/analysis/pseudobulk/__init__.py
singlecell_cookbook/tools/analysis/pseudobulk/_edger.py
singlecell_cookbook/tools/analysis/pseudobulk/utils/__init__.py
singlecell_cookbook/tools/analysis/pseudobulk/utils/_aggregate_and_filter.py
singlecell_cookbook/tools/preprocess/__init__.py
singlecell_cookbook/tools/preprocess/_subset.py
singlecell_cookbook/tools/preprocess/_transform.py
singlecell_cookbook/tools/preprocess/_utils.py
singlecell_cookbook-0.3.1.dist-info/METADATA
singlecell_cookbook-0.3.1.dist-info/WHEEL
singlecell_cookbook-0.3.1.dist-info/licenses/LICENSE.md
singlecell_cookbook-0.3.1.dist-info/RECORD
