Metadata-Version: 2.4
Name: singlecell-cookbook
Version: 0.3.1
Summary: A collection of tools for analyzing single-cell genomics data.
Project-URL: Homepage, https://github.com/argearriojas/singlecell-cookbook
Project-URL: Documentation, https://singlecell-cookbook.readthedocs.io
Project-URL: Repository, https://github.com/argearriojas/singlecell-cookbook
Project-URL: Issues, https://github.com/argearriojas/singlecell-cookbook/issues
Project-URL: Release Notes, https://github.com/argearriojas/singlecell-cookbook/releases
Author-email: Argenis Arriojas <arriojasmaldonado001@umb.edu>
License: MIT License
License-File: LICENSE.md
Keywords: RNA-seq,analysis,bioinformatics,genomics,single-cell
Classifier: Development Status :: 3 - Alpha
Classifier: Intended Audience :: Developers
Classifier: Operating System :: OS Independent
Classifier: Programming Language :: Python :: 3
Classifier: Programming Language :: Python :: 3.11
Classifier: Programming Language :: Python :: 3.12
Requires-Python: <3.13,>=3.11
Requires-Dist: anndata
Requires-Dist: numpy
Requires-Dist: pandas
Requires-Dist: scanpy
Requires-Dist: scipy
Provides-Extra: dev
Requires-Dist: anndata2ri>=1.3; extra == 'dev'
Requires-Dist: bump2version~=1.0.1; extra == 'dev'
Requires-Dist: myst-parser~=4.0.0; extra == 'dev'
Requires-Dist: pre-commit~=4.0.1; extra == 'dev'
Requires-Dist: pytest~=8.3.3; extra == 'dev'
Requires-Dist: rpy2>=3.5.14; extra == 'dev'
Requires-Dist: ruff~=0.8.0; extra == 'dev'
Requires-Dist: sphinx-autodoc-typehints~=2.5.0; extra == 'dev'
Requires-Dist: sphinx-rtd-theme~=3.0.1; extra == 'dev'
Requires-Dist: sphinx~=8.1.3; extra == 'dev'
Provides-Extra: docs
Requires-Dist: myst-parser~=4.0.0; extra == 'docs'
Requires-Dist: sphinx-autodoc-typehints~=2.5.0; extra == 'docs'
Requires-Dist: sphinx-rtd-theme~=3.0.1; extra == 'docs'
Requires-Dist: sphinx~=8.1.3; extra == 'docs'
Provides-Extra: r
Requires-Dist: anndata2ri>=1.3; extra == 'r'
Requires-Dist: rpy2>=3.5.14; extra == 'r'
Provides-Extra: test
Requires-Dist: pytest~=8.3.3; extra == 'test'
